package/__init__.py
package/main.py
IGEMforMinerals-1.0.0.dist-info/LICENSE
IGEMforMinerals-1.0.0.dist-info/METADATA
IGEMforMinerals-1.0.0.dist-info/WHEEL
IGEMforMinerals-1.0.0.dist-info/top_level.txt
IGEMforMinerals-1.0.0.dist-info/RECORD
